autolei/__init__.py
autolei/_run.bat
autolei/autolei.py
autolei/autolei_core.py
autolei/instrument_profile/Ceta-1k-200kV
autolei/instrument_profile/Ceta-2k-200kV
autolei/instrument_profile/Ceta-512-200kV
autolei/instrument_profile/Ceta-D-1024-SciLifeLab
autolei/instrument_profile/Ceta-D-2k-SciLifeLab
autolei/instrument_profile/Ceta-D-512-SciLifeLab
autolei/instrument_profile/Chettah-Themis-Z_SU
autolei/instrument_profile/Oneview-Themis-Z_SU
autolei/instrument_profile/TimePix-512_2100_SU
autolei/instrument_profile/TimePix-516_2100_SU
autolei/instrument_profile/__init__.py
autolei/qt/style.qss
autolei/realtime.py
autolei/setting.ini
autolei/src/_XDSINP
autolei/src/__init__.py
autolei/src/analysis_hkl/__init__.py
autolei/src/analysis_hkl/analyser.py
autolei/src/analysis_hkl/cell_distance.py
autolei/src/analysis_hkl/cell_reduction.py
autolei/src/analysis_hkl/generate_hkl.py
autolei/src/analysis_hkl/lattice_symm.py
autolei/src/analysis_hkl/load_file.py
autolei/src/analysis_hkl/metrics.py
autolei/src/analysis_hkl/refl_combine.py
autolei/src/analysis_hkl/util.py
autolei/src/cif_io.py
autolei/src/extinction.json
autolei/src/file_io/__init__.py
autolei/src/file_io/folder_move_manager.py
autolei/src/image_io/__init__.py
autolei/src/image_io/beam_centre.py
autolei/src/image_io/beam_stop.py
autolei/src/image_io/generate_pets.py
autolei/src/image_io/mrc.py
autolei/src/image_io/nxs.py
autolei/src/image_io/tiff.py
autolei/src/symm_shelx/__init__.py
autolei/src/symm_shelx/laue_symm_ops.py
autolei/src/symm_shelx/make_shelx_ins.py
autolei/src/symm_shelx/shelx_symm_ops.py
autolei/src/symm_shelx/space_group_finder.py
autolei/src/symm_shelx/symm_function.py
autolei/src/util.py
autolei/src/visualisation/__init__.py
autolei/src/visualisation/html_report.py
autolei/src/visualisation/recip_viewer.py
autolei/src/visualisation/recip_viewer_GUI.py
autolei/src/xds_analysis.py
autolei/src/xds_cluster.py
autolei/src/xds_input.py
autolei/src/xds_refine.py
autolei/src/xds_refiner/__init__.py
autolei-1.0.2.250711.dist-info/LICENSE
autolei-1.0.2.250711.dist-info/METADATA
autolei-1.0.2.250711.dist-info/WHEEL
autolei-1.0.2.250711.dist-info/entry_points.txt
autolei-1.0.2.250711.dist-info/RECORD
