Metadata-Version: 2.3
Name: autolei
Version: 1.0.2.250711
Summary: A GUI for electron diffraction data analysis
License: BSD 3-Clause
Keywords: electron-diffraction,XDS,microed,data-analysis,automation,crystallography
Author: Lei Wang
Author-email: lei.wang@su.se
Requires-Python: >=3.8,<4.0
Classifier: Development Status :: 4 - Beta
Classifier: Intended Audience :: Science/Research
Classifier: License :: OSI Approved :: BSD License
Classifier: License :: Other/Proprietary License
Classifier: Operating System :: MacOS :: MacOS X
Classifier: Operating System :: POSIX :: Linux
Classifier: Programming Language :: Python :: 3
Classifier: Programming Language :: Python :: 3.8
Classifier: Programming Language :: Python :: 3.9
Classifier: Programming Language :: Python :: 3.10
Classifier: Programming Language :: Python :: 3.11
Classifier: Programming Language :: Python :: 3.12
Classifier: Programming Language :: Python :: 3.13
Classifier: Topic :: Scientific/Engineering :: Chemistry
Classifier: Topic :: Scientific/Engineering :: Physics
Requires-Dist: PyQt5 (>=5.15.0)
Requires-Dist: fabio (>=0.14.0)
Requires-Dist: h5py (>=3.1.0)
Requires-Dist: hdf5plugin (>=3.3.1)
Requires-Dist: matplotlib (>=3.3.4,<3.12)
Requires-Dist: mplcursors (>=0.5.1)
Requires-Dist: mrcfile (>=1.5.0)
Requires-Dist: numba (>=0.53.0)
Requires-Dist: numpy (>=1.19.5)
Requires-Dist: openpyxl (>=3.0.0)
Requires-Dist: pandas (>=1.1.5)
Requires-Dist: pillow (>=8.0.0)
Requires-Dist: plotly (>=5.0.0)
Requires-Dist: scikit-image (>=0.18.0)
Requires-Dist: scipy (>=1.5.4)
Requires-Dist: spglib (>=1.9.0)
Requires-Dist: tqdm (>=4.46.1)
Project-URL: Bug Reports, https://gitlab.com/395736627tristone/automicroedgui/issues
Project-URL: Documentation, https://gitlab.com/395736627tristone/automicroedgui/docs
Project-URL: Homepage, https://gitlab.com/395736627tristone/automicroedgui
Project-URL: Repository, https://gitlab.com/395736627tristone/automicroedgui
